bagel/__init__.py
bagel/config.py
bagel/errors.py
bagel/api/Cluster.py
bagel/api/__init__.py
bagel/api/fastapi.py
bagel/api/types.py
bagel/utils/__init__.py
test/__init__.py
test/client_test.py
test/opt_test.py
bagelML-0.1.3.dist-info/METADATA
bagelML-0.1.3.dist-info/WHEEL
bagelML-0.1.3.dist-info/top_level.txt
bagelML-0.1.3.dist-info/RECORD
