Metadata-Version: 2.1
Name: bagelML
Version: 0.1.3
Summary: BagelML is a library for Bagel's finetuning API.
Home-page: https://github.com/BagelNetwork/Client
Author: Bidhan Roy
Author-email: bidhan@bagel.net
Classifier: Development Status :: 3 - Alpha
Classifier: Intended Audience :: Developers
Classifier: License :: OSI Approved :: MIT License
Classifier: Operating System :: OS Independent
Classifier: Programming Language :: Python
Classifier: Programming Language :: Python :: 3
Classifier: Programming Language :: Python :: 3.7
Classifier: Programming Language :: Python :: 3.8
Classifier: Programming Language :: Python :: 3.9
Classifier: Programming Language :: Python :: 3.10
Classifier: Topic :: Software Development :: Libraries :: Python Modules
Classifier: Topic :: Scientific/Engineering :: Artificial Intelligence
Requires-Dist: certifi>=2023.5.7
Requires-Dist: charset-normalizer>=3.2.0
Requires-Dist: graphlib-backport>=1.0.3
Requires-Dist: idna>=3.4
Requires-Dist: numpy>=1.21.6
Requires-Dist: overrides>=7.3.1
Requires-Dist: pandas>=2.0.1
Requires-Dist: pydantic<2.0,>=1.10.10
Requires-Dist: python-dateutil>=2.8.2
Requires-Dist: pytz>=2023.3
Requires-Dist: requests>=2.28
Requires-Dist: six>=1.16.0
Requires-Dist: typing-extensions>=4.6.3
Requires-Dist: urllib3>=1.26.16
Requires-Dist: tzdata>=2022.1
